{"is_source_file": true, "format": "TypeScript (TSX)", "description": "Defines a React functional component 'Board' that renders a 3x3 grid of 'Square' components for a Tic Tac Toe game, including styling and accessibility attributes.", "external_files": ["./Square", "../theme"], "external_methods": ["Square", "cx"], "published": ["Board"], "classes": [], "methods": [{"name": "Board", "description": "React functional component that renders a Tic Tac Toe board as a grid of Squares, accepts props for the board state, play handler, and disabled state."}], "calls": ["board.map", "Square"], "search-terms": ["React", "Tic Tac Toe", "Board component", "Square", "grid layout", "tsx", "styling", "props"], "state": 2, "file_id": 18, "knowledge_revision": 37, "git_revision": "", "ctags": [], "hash": "40c330dee8e142c4181a4ac842e9e6d3", "format-version": 4, "code-base-name": "tic_tac_toe_frontend", "filename": "tic_tac_toe_frontend/src/components/Board.tsx", "revision_history": [{"37": ""}]}